[{"n_candidate": 1, "recall": 0.0030000000000000005}, {"n_candidate": 2, "recall": 0.008}, {"n_candidate": 4, "recall": 0.016}, {"n_candidate": 8, "recall": 0.035}, {"n_candidate": 16, "recall": 0.078}, {"n_candidate": 32, "recall": 0.138}, {"n_candidate": 64, "recall": 0.23200000000000004}, {"n_candidate": 128, "recall": 0.402}, {"n_candidate": 256, "recall": 0.618}, {"n_candidate": 512, "recall": 0.8059999999999999}, {"n_candidate": 1024, "recall": 0.9220000000000002}, {"n_candidate": 2048, "recall": 0.982}, {"n_candidate": 4096, "recall": 1.0}, {"n_candidate": 8192, "recall": 1.0}]