{"total_time_consume": 6.854839563369751, "preprocess": {"total_time": 0.43479061126708984}, "classifier": [{"ins_id": 1, "dataset_partition": {"time": 0.015462875366210938, "cluster_number_distribution": [4138, 5862]}, "predict": {"time": 0.0001995563507080078}}, {"ins_id": 2, "dataset_partition": {"time": 0.008860349655151367, "cluster_number_distribution": [4509, 5491]}, "predict": {"time": 0.0001647472381591797}}, {"ins_id": 3, "dataset_partition": {"time": 0.004676103591918945, "cluster_number_distribution": [5362, 4638]}, "predict": {"time": 0.00013303756713867188}}, {"ins_id": 4, "dataset_partition": {"time": 0.004440784454345703, "cluster_number_distribution": [4618, 5382]}, "predict": {"time": 0.0001277923583984375}}, {"ins_id": 5, "dataset_partition": {"time": 0.0044155120849609375, "cluster_number_distribution": [4916, 5084]}, "predict": {"time": 0.00012564659118652344}}, {"ins_id": 6, "dataset_partition": {"time": 0.004443645477294922, "cluster_number_distribution": [4936, 5064]}, "predict": {"time": 0.00012731552124023438}}, {"ins_id": 7, "dataset_partition": {"time": 0.004369974136352539, "cluster_number_distribution": [4938, 5062]}, "predict": {"time": 0.00012803077697753906}}, {"ins_id": 8, "dataset_partition": {"time": 0.004449605941772461, "cluster_number_distribution": [5730, 4270]}, "predict": {"time": 0.00012731552124023438}}, {"ins_id": 9, "dataset_partition": {"time": 0.0044558048248291016, "cluster_number_distribution": [4974, 5026]}, "predict": {"time": 0.0001246929168701172}}, {"ins_id": 10, "dataset_partition": {"time": 0.004393815994262695, "cluster_number_distribution": [6304, 3696]}, "predict": {"time": 0.00011420249938964844}}, {"ins_id": 11, "dataset_partition": {"time": 0.004368782043457031, "cluster_number_distribution": [5797, 4203]}, "predict": {"time": 0.00012731552124023438}}, {"ins_id": 12, "dataset_partition": {"time": 0.004376411437988281, "cluster_number_distribution": [5753, 4247]}, "predict": {"time": 0.00012302398681640625}}, {"ins_id": 13, "dataset_partition": {"time": 0.004376888275146484, "cluster_number_distribution": [4582, 5418]}, "predict": {"time": 0.00012254714965820312}}, {"ins_id": 14, "dataset_partition": {"time": 0.004395008087158203, "cluster_number_distribution": [5184, 4816]}, "predict": {"time": 0.00012493133544921875}}, {"ins_id": 15, "dataset_partition": {"time": 0.0043413639068603516, "cluster_number_distribution": [3721, 6279]}, "predict": {"time": 0.0001220703125}}, {"ins_id": 16, "dataset_partition": {"time": 0.004572391510009766, "cluster_number_distribution": [4613, 5387]}, "predict": {"time": 0.00012063980102539062}}], "integrate": {"time": 6.117898941040039}, "count_recall": {"time": 0.19042730331420898}}