[{"n_candidate": 1, "recall": 0.001}, {"n_candidate": 2, "recall": 0.001}, {"n_candidate": 4, "recall": 0.005}, {"n_candidate": 8, "recall": 0.025}, {"n_candidate": 16, "recall": 0.06199999999999999}, {"n_candidate": 32, "recall": 0.10300000000000001}, {"n_candidate": 64, "recall": 0.165}, {"n_candidate": 128, "recall": 0.24700000000000005}, {"n_candidate": 256, "recall": 0.36800000000000005}, {"n_candidate": 512, "recall": 0.5189999999999999}, {"n_candidate": 1024, "recall": 0.6669999999999999}, {"n_candidate": 2048, "recall": 0.836}, {"n_candidate": 4096, "recall": 0.9610000000000001}, {"n_candidate": 8192, "recall": 0.9990000000000001}]